[{"productInBill":[{"productNumber":2,"productName":"Sản phẩm B","price":200000,"number":5,"total":1000000}],"numberBillOut":1,"createDate":"0001-01-01T00:00:00"},{"productInBill":[],"numberBillOut":2,"createDate":"0001-01-01T00:00:00"},{"productInBill":[{"productNumber":2,"productName":"Sản phẩm B","price":200000,"number":4,"total":800000}],"numberBillOut":3,"createDate":"0001-01-01T00:00:00"},{"productInBill":[{"productNumber":2,"productName":"Sản phẩm B","price":200000,"number":2,"total":400000}],"numberBillOut":4,"createDate":"0001-01-01T00:00:00"},{"productInBill":[{"productNumber":4,"productName":"San pham PPPP2134","price":99,"number":50,"total":4950}],"numberBillOut":5,"createDate":"0001-01-01T00:00:00"},{"productInBill":[{"productNumber":2,"productName":"Sản phẩm B","price":200000,"number":6,"total":1200000}],"numberBillOut":6,"createDate":"0001-01-01T00:00:00"}]
